{
    "key": "group_66852f2beee57",
    "title": "About Us B",
    "fields": [
        {
            "key": "field_66852f2caf253",
            "label": "About Us B",
            "name": "about_us_b",
            "aria-label": "",
            "type": "group",
            "instructions": "",
            "required": 0,
            "conditional_logic": 0,
            "wrapper": {
                "width": "",
                "class": "",
                "id": ""
            },
            "layout": "block",
            "sub_fields": [
                {
                    "key": "field_66852fc4af254",
                    "label": "About us content left",
                    "name": "about_us_content",
                    "aria-label": "",
                    "type": "group",
                    "instructions": "",
                    "required": 0,
                    "conditional_logic": 0,
                    "wrapper": {
                        "width": "50",
                        "class": "",
                        "id": ""
                    },
                    "layout": "block",
                    "sub_fields": [
                        {
                            "key": "field_668530db5c91c",
                            "label": "About Us content heading",
                            "name": "about_us_content_heading",
                            "aria-label": "",
                            "type": "text",
                            "instructions": "",
                            "required": 0,
                            "conditional_logic": 0,
                            "wrapper": {
                                "width": "",
                                "class": "",
                                "id": ""
                            },
                            "default_value": "",
                            "maxlength": "",
                            "placeholder": "",
                            "prepend": "",
                            "append": ""
                        },
                        {
                            "key": "field_6685302faf258",
                            "label": "About us block Description",
                            "name": "about_us_block_description",
                            "aria-label": "",
                            "type": "text",
                            "instructions": "",
                            "required": 0,
                            "conditional_logic": 0,
                            "wrapper": {
                                "width": "",
                                "class": "",
                                "id": ""
                            },
                            "default_value": "",
                            "maxlength": "",
                            "placeholder": "",
                            "prepend": "",
                            "append": ""
                        },
                        {
                            "key": "field_6685303eaf259",
                            "label": "About us content Button",
                            "name": "about_us_content_button",
                            "aria-label": "",
                            "type": "link",
                            "instructions": "",
                            "required": 0,
                            "conditional_logic": 0,
                            "wrapper": {
                                "width": "",
                                "class": "",
                                "id": ""
                            },
                            "return_format": ""
                        }
                    ]
                },
                {
                    "key": "field_6685305caf25a",
                    "label": "About us media  Right",
                    "name": "about_us_media_right",
                    "aria-label": "",
                    "type": "group",
                    "instructions": "",
                    "required": 0,
                    "conditional_logic": 0,
                    "wrapper": {
                        "width": "50",
                        "class": "",
                        "id": ""
                    },
                    "layout": "block",
                    "sub_fields": [
                        {
                            "key": "field_6685305caf25b",
                            "label": "About Us block media Title",
                            "name": "about_us_block_media_title",
                            "aria-label": "",
                            "type": "text",
                            "instructions": "",
                            "required": 0,
                            "conditional_logic": 0,
                            "wrapper": {
                                "width": "",
                                "class": "",
                                "id": ""
                            },
                            "default_value": "",
                            "maxlength": "",
                            "placeholder": "",
                            "prepend": "",
                            "append": ""
                        },
                        {
                            "key": "field_668537ea9c03f",
                            "label": "About Us block media Image",
                            "name": "about_us_block_media_image",
                            "aria-label": "",
                            "type": "image",
                            "instructions": "",
                            "required": 0,
                            "conditional_logic": 0,
                            "wrapper": {
                                "width": "",
                                "class": "",
                                "id": ""
                            },
                            "return_format": "array",
                            "library": "all",
                            "min_width": "",
                            "min_height": "",
                            "min_size": "",
                            "max_width": "",
                            "max_height": "",
                            "max_size": "",
                            "mime_types": "",
                            "preview_size": "medium"
                        },
                        {
                            "key": "field_6685305caf25d",
                            "label": "About us content media link",
                            "name": "about_us_content_media_link",
                            "aria-label": "",
                            "type": "link",
                            "instructions": "",
                            "required": 0,
                            "conditional_logic": 0,
                            "wrapper": {
                                "width": "",
                                "class": "",
                                "id": ""
                            },
                            "return_format": "array"
                        }
                    ]
                }
            ]
        }
    ],
    "location": [
        [
            {
                "param": "block",
                "operator": "==",
                "value": "acf\/about-us-b"
            }
        ]
    ],
    "menu_order": 0,
    "position": "normal",
    "style": "default",
    "label_placement": "top",
    "instruction_placement": "label",
    "hide_on_screen": "",
    "active": true,
    "description": "",
    "show_in_rest": 0,
    "modified": 1720006769
}
